airflowx/__init__.py
airflowx/security/__init__.py
airflowx/security/rbac/__init__.py
airflowx/security/rbac/internal/__init__.py
airflowx/security/rbac/internal/provider.py
airflowx/security/rbac/internal/sql.py
airflowx/security/rbac/operator/__init__.py
airflowx/security/rbac/operator/base.py
airflowx/security/rbac/operator/postgres.py
airflowx/security/rbac/sqlalchemy.py
airflowx-0.1.0.dist-info/METADATA
airflowx-0.1.0.dist-info/WHEEL
airflowx-0.1.0.dist-info/RECORD
