Metadata-Version: 2.1
Name: airflowx
Version: 0.1.0
Summary: 
Author: amArbaoui
Author-email: adel.arbaoui@gmail.com
Requires-Python: >=3.9,<4.0
Classifier: Programming Language :: Python :: 3
Classifier: Programming Language :: Python :: 3.9
Classifier: Programming Language :: Python :: 3.10
Classifier: Programming Language :: Python :: 3.11
Classifier: Programming Language :: Python :: 3.12
Requires-Dist: apache-airflow (>=2.6.0,<3.0.0)
Requires-Dist: apache-airflow-providers-postgres (>=5.3.0,<6.0.0)
Requires-Dist: psycopg2-binary (>=2.9.9,<3.0.0)
Requires-Dist: pymysql (>=1.1.0,<2.0.0)
Requires-Dist: sqlalchemy (>=1.4,<1.5)
